__init__.py
config.py
main.py
apple_music_import-0.1.2.dist-info/licenses/LICENSE
folder_classes/__init__.py
folder_classes/bandcamp_folder.py
folder_classes/soulseek_folder.py
lib/__init__.py
lib/abstract_album_folder.py
lib/apple_music.py
lib/constants.py
lib/cover_image.py
lib/file_convertor.py
lib/helpers.py
lib/logger.py
apple_music_import-0.1.2.dist-info/METADATA
apple_music_import-0.1.2.dist-info/WHEEL
apple_music_import-0.1.2.dist-info/top_level.txt
apple_music_import-0.1.2.dist-info/RECORD
