Metadata-Version: 2.4
Name: apple-music-import
Version: 0.1.2
Summary: convert, tag cover images, and import music files into Apple Music
Author-email: Arjun Ray <deconstructionalism@gmail.com>
License-Expression: MIT
Project-URL: Homepage, https://github.com/deconstructionalism/apple_music_import
Project-URL: Issues, https://github.com/deconstructionalism/apple_music_import/issues
Classifier: Programming Language :: Python :: 3
Classifier: Operating System :: MacOS :: MacOS X
Requires-Python: >=3.10
License-File: LICENSE
Requires-Dist: mutagen>=1.47.0
Requires-Dist: pydub>=0.25.1
Requires-Dist: requests>=2.32.3
Requires-Dist: send2trash>=1.8.3
Dynamic: license-file
